uunet/_multinet.pypy39-pp73-darwin.so
uunet/multinet.py
uunet/__init__.py
uunet/data/bankwiring.mpx
uunet/data/florentine.mpx
uunet/data/aucs.mpx
uunet/data/tailorshop.mpx
uunet/data/book.mpx
uunet/data/monastery.mpx
uunet-2.2.1.dist-info/RECORD
uunet-2.2.1.dist-info/LICENSE
uunet-2.2.1.dist-info/WHEEL
uunet-2.2.1.dist-info/top_level.txt
uunet-2.2.1.dist-info/METADATA
