Metadata-Version: 2.1
Name: uunet
Version: 2.2.1
Summary: Python porting of the multinet library
Author-email: Matteo Magnani <matteo.magnani@it.uu.se>
License: Apache 2.0
Project-URL: homepage, https://github.com/uuinfolab/py_multinet
Keywords: network analysis,multilayer
Classifier: Programming Language :: Python :: 3
Classifier: License :: OSI Approved :: Apache Software License
Classifier: Operating System :: OS Independent
Requires-Python: >=3.8
License-File: LICENSE
Requires-Dist: networkx
Requires-Dist: matplotlib
